abhanti/__init__.py
abhanti/client.py
abhanti/exceptions.py
abhanti-1.0.0.dist-info/licenses/LICENSE
abhanti-1.0.0.dist-info/METADATA
abhanti-1.0.0.dist-info/WHEEL
abhanti-1.0.0.dist-info/top_level.txt
abhanti-1.0.0.dist-info/RECORD
